<?xml version="1.0" encoding="UTF-8"?>
<feature
      id="org.polymap.rhei.ide.feature"
      label="Rhei Framework"
      version="2.1.0.qualifier"
      provider-name="polymap.org">

   <description url="http://polymap.org/polymap3/wiki/Rhei/Start.de">
      Provides an Integrated Development Environment inside the Polymap3 Workbench that allows to develop domain specific application for the Rhei framework.
   </description>

   <copyright url="http://www.example.com/copyright">
      Copyright (C) 2009-2014  by the programmers of the Rhei Framework as tagged in the code. All rights reserved.
   </copyright>

   <license>
      LGPL
   </license>

   <requires>
      <import feature="org.polymap.core.feature" version="3.1.0.qualifier" match="compatible"/>
      <import feature="org.polymap.rhei.feature" version="2.0.0.qualifier" match="compatible"/>
   </requires>

   <plugin
         id="org.polymap.rhei.ide"
         download-size="0"
         install-size="0"
         version="0.0.0"/>

   <plugin
         id="org.eclipse.ui.ide"
         download-size="0"
         install-size="0"
         version="0.0.0"
         unpack="false"/>

   <plugin
         id="org.eclipse.jface.text"
         download-size="0"
         install-size="0"
         version="0.0.0"
         unpack="false"/>

   <plugin
         id="org.eclipse.text"
         download-size="0"
         install-size="0"
         version="0.0.0"
         unpack="false"/>

   <plugin
         id="org.eclipse.core.filesystem"
         download-size="0"
         install-size="0"
         version="0.0.0"
         unpack="false"/>

   <plugin
         id="org.eclipse.jdt.core"
         download-size="0"
         install-size="0"
         version="0.0.0"
         unpack="false"/>

</feature>
